demo_pypi_test/__init__.py
demo_pypi_test/main.py
demo_pypi_test-0.0.3.dist-info/METADATA
demo_pypi_test-0.0.3.dist-info/WHEEL
demo_pypi_test-0.0.3.dist-info/entry_points.txt
demo_pypi_test-0.0.3.dist-info/top_level.txt
demo_pypi_test-0.0.3.dist-info/RECORD
