Metadata-Version: 2.4
Name: demo_pypi_test
Version: 0.0.3
Author: Agnish Choudhury
Dynamic: author
Dynamic: description
Dynamic: description-content-type
